atlaslib_ecmwf/__init__.py
atlaslib_ecmwf/bin/atlas
atlaslib_ecmwf/bin/atlas-atest-mgrids
atlaslib_ecmwf/bin/atlas-gaussian-latitudes
atlaslib_ecmwf/bin/atlas-grid-points
atlaslib_ecmwf/bin/atlas-grids
atlaslib_ecmwf/bin/atlas-meshgen
atlaslib_ecmwf/bin/pluto-benchmark
atlaslib_ecmwf/include/atlas/array.h
atlaslib_ecmwf/include/atlas/array_fwd.h
atlaslib_ecmwf/include/atlas/atlas.h
atlaslib_ecmwf/include/atlas/atlas_ecbuild_config.h
atlaslib_ecmwf/include/atlas/domain.h
atlaslib_ecmwf/include/atlas/field.h
atlaslib_ecmwf/include/atlas/functionspace.h
atlaslib_ecmwf/include/atlas/grid.h
atlaslib_ecmwf/include/atlas/interpolation.h
atlaslib_ecmwf/include/atlas/library.h
atlaslib_ecmwf/include/atlas/mesh.h
atlaslib_ecmwf/include/atlas/meshgenerator.h
atlaslib_ecmwf/include/atlas/option.h
atlaslib_ecmwf/include/atlas/projection.h
atlaslib_ecmwf/include/atlas/array/Array.h
atlaslib_ecmwf/include/atlas/array/ArrayDataStore.h
atlaslib_ecmwf/include/atlas/array/ArrayIdx.h
atlaslib_ecmwf/include/atlas/array/ArrayLayout.h
atlaslib_ecmwf/include/atlas/array/ArrayShape.h
atlaslib_ecmwf/include/atlas/array/ArraySpec.h
atlaslib_ecmwf/include/atlas/array/ArrayStrides.h
atlaslib_ecmwf/include/atlas/array/ArrayView.h
atlaslib_ecmwf/include/atlas/array/ArrayViewDefs.h
atlaslib_ecmwf/include/atlas/array/ArrayViewUtil.h
atlaslib_ecmwf/include/atlas/array/ArrayViewVariant.h
atlaslib_ecmwf/include/atlas/array/DataType.h
atlaslib_ecmwf/include/atlas/array/IndexView.h
atlaslib_ecmwf/include/atlas/array/LocalView.h
atlaslib_ecmwf/include/atlas/array/MakeView.h
atlaslib_ecmwf/include/atlas/array/Range.h
atlaslib_ecmwf/include/atlas/array/SVector.h
atlaslib_ecmwf/include/atlas/array/Table.h
atlaslib_ecmwf/include/atlas/array/TableView.h
atlaslib_ecmwf/include/atlas/array/Vector.h
atlaslib_ecmwf/include/atlas/array/gridtools/GridToolsArrayHelpers.h
atlaslib_ecmwf/include/atlas/array/gridtools/GridToolsArrayView.h
atlaslib_ecmwf/include/atlas/array/gridtools/GridToolsDataStore.h
atlaslib_ecmwf-0.43.1.dist-info/licenses/AUTHORS
atlaslib_ecmwf-0.43.1.dist-info/licenses/LICENSE
atlaslib_ecmwf-0.43.1.dist-info/METADATA
atlaslib_ecmwf-0.43.1.dist-info/WHEEL
atlaslib_ecmwf-0.43.1.dist-info/top_level.txt
atlaslib_ecmwf-0.43.1.dist-info/RECORD
