Metadata-Version: 2.4
Name: atlaslib-ecmwf
Version: 0.43.1
Summary: "atlaslib-ecmwf"
Author: file: AUTHORS
License-File: LICENSE
License-File: AUTHORS
Requires-Dist: eckitlib<2,>=1.29.2
Dynamic: license-file
Dynamic: requires-dist
